pibayer/__init__.py
pibayer-0.5.0.dist-info/DESCRIPTION.rst
pibayer-0.5.0.dist-info/METADATA
pibayer-0.5.0.dist-info/RECORD
pibayer-0.5.0.dist-info/WHEEL
pibayer-0.5.0.dist-info/metadata.json
pibayer-0.5.0.dist-info/top_level.txt
