Metadata-Version: 2.0
Name: pibayer
Version: 0.5.0
Summary: Acquire raw Bayer-masked image from Raspberry Pi camera and write to HDF5 or TIFF.
Home-page: https://github.com/scivision/raspicam-raw-bayer
Author: Michael Hirsch, Ph.D.
Author-email: UNKNOWN
License: UNKNOWN
Platform: UNKNOWN
Classifier: Intended Audience :: Science/Research
Classifier: Development Status :: 4 - Beta
Classifier: License :: OSI Approved :: MIT License
Classifier: Topic :: Scientific/Engineering :: Medical Science Apps.
Classifier: Programming Language :: Python :: 3
Requires-Dist: nose
Requires-Dist: numpy
Requires-Dist: picamera
Provides-Extra: plot
Requires-Dist: matplotlib; extra == 'plot'
Provides-Extra: write
Requires-Dist: h5py; extra == 'write'
Requires-Dist: tifffile; extra == 'write'
